README.rst
setup.cfg
setup.py
lazy_import/VERSION
lazy_import/__init__.py
lazy_import/test_lazy.py
lazy_import.egg-info/PKG-INFO
lazy_import.egg-info/SOURCES.txt
lazy_import.egg-info/dependency_links.txt
lazy_import.egg-info/requires.txt
lazy_import.egg-info/top_level.txt